botogram/__init__.py
botogram/api.py
botogram/bot.py
botogram/callbacks.py
botogram/commands.py
botogram/components.py
botogram/context.py
botogram/crypto.py
botogram/decorators.py
botogram/defaults.py
botogram/frozenbot.py
botogram/hooks.py
botogram/messages.py
botogram/shared.py
botogram/syntaxes.py
botogram/tasks.py
botogram/updates.py
botogram/i18n/br.mo
botogram/i18n/en.mo
botogram/i18n/it.mo
botogram/i18n/pt.mo
botogram/objects/__init__.py
botogram/objects/base.py
botogram/objects/callbacks.py
botogram/objects/chats.py
botogram/objects/markup.py
botogram/objects/media.py
botogram/objects/messages.py
botogram/objects/mixins.py
botogram/objects/polls.py
botogram/objects/updates.py
botogram/runner/__init__.py
botogram/runner/ipc.py
botogram/runner/jobs.py
botogram/runner/processes.py
botogram/runner/shared.py
botogram/utils/__init__.py
botogram/utils/calls.py
botogram/utils/deprecations.py
botogram/utils/startup.py
botogram/utils/strings.py
botogram2-0.6.1.dist-info/AUTHORS
botogram2-0.6.1.dist-info/LICENSE
botogram2-0.6.1.dist-info/METADATA
botogram2-0.6.1.dist-info/WHEEL
botogram2-0.6.1.dist-info/top_level.txt
botogram2-0.6.1.dist-info/RECORD
